versioned_hdf5/__init__.py
versioned_hdf5/api.py
versioned_hdf5/backend.py
versioned_hdf5/cytools.cpython-313-aarch64-linux-gnu.so
versioned_hdf5/h5py_compat.py
versioned_hdf5/hashtable.py
versioned_hdf5/replay.py
versioned_hdf5/slicetools.cpython-313-aarch64-linux-gnu.so
versioned_hdf5/staged_changes.cpython-313-aarch64-linux-gnu.so
versioned_hdf5/subchunk_map.cpython-313-aarch64-linux-gnu.so
versioned_hdf5/tools.py
versioned_hdf5/typing_.py
versioned_hdf5/versions.py
versioned_hdf5/wrappers.py
versioned_hdf5-2.2.1.dist-info/LICENSE
versioned_hdf5-2.2.1.dist-info/METADATA
versioned_hdf5-2.2.1.dist-info/WHEEL
versioned_hdf5-2.2.1.dist-info/RECORD
