Metadata-Version: 2.1
Name: versioned-hdf5
Version: 2.2.1
Summary: Versioned HDF5 provides a versioned abstraction on top of h5py
Author: Quansight
License: BSD License
Classifier: Programming Language :: Python :: 3
Classifier: License :: OSI Approved :: BSD License
Classifier: Operating System :: OS Independent
Project-URL: Homepage, https://github.com/deshaw/versioned-hdf5
Requires-Python: >=3.10
Requires-Dist: numpy>=1.24.4
Requires-Dist: h5py>=3.15.0
Requires-Dist: ndindex>=1.5.1
Provides-Extra: dev
Requires-Dist: pre-commit>=3.6.0; extra == "dev"
Requires-Dist: cython; extra == "dev"
Requires-Dist: meson-python; extra == "dev"
Requires-Dist: setuptools-scm; extra == "dev"
Provides-Extra: test
Requires-Dist: pytest; extra == "test"
Requires-Dist: pytest-env; extra == "test"
Requires-Dist: hypothesis; extra == "test"
Requires-Dist: packaging; extra == "test"
Provides-Extra: doc
Requires-Dist: sphinx; extra == "doc"
Requires-Dist: sphinx-multiversion; extra == "doc"
Requires-Dist: myst-parser; extra == "doc"
Provides-Extra: bench
Requires-Dist: asv; extra == "bench"
